maintain_PlatoUtils/__init__.py
maintain_PlatoUtils/maintain_PlatoUtils.py
maintain_PlatoUtils/maintain_csv2platodb_A_uploadFile.py
maintain_PlatoUtils/maintain_csv2platodb_B_submitSchema.py
maintain_PlatoUtils/maintain_csv2platodb_C_import.py
maintain_PlatoUtils/uploadFiles2PlatoServer.py
maintain_PlatoUtils/GraphWrapClient/GraphWrapClient.py
maintain_PlatoUtils/GraphWrapClient/__init__.py
maintain_PlatoUtils/algorithms/GraphEmbeding.py
maintain_PlatoUtils/algorithms/RelationRecognizer.py
maintain_PlatoUtils/algorithms/__init__.py
maintain_PlatoUtils/text_utils/__init__.py
maintain_PlatoUtils/text_utils/afterprocessor.py
maintain_PlatoUtils/text_utils/preprocessor.py
maintain_PlatoUtils/text_utils/tryTfidfSearch.py
maintain_PlatoUtils/text_utils/staticData/__init__.py
maintain_PlatoUtils/text_utils/staticData/locImpDict.py
maintain_PlatoUtils/text_utils/staticData/stopwords.py
maintain_PlatoUtils/v2/__init__.py
maintain_PlatoUtils/v2/maintain_PlatoUtils.py
maintain_PlatoUtils/v2/maintain_csv2platodb_A_uploadFile.py
maintain_PlatoUtils/v2/maintain_csv2platodb_B_submitSchema.py
maintain_PlatoUtils/v2/maintain_csv2platodb_C_import.py
maintain_PlatoUtils/v2/uploadFiles2PlatoServer.py
maintain_PlatoUtils/v2/GraphWrapClient/GraphWrapClient.py
maintain_PlatoUtils/v2/GraphWrapClient/__init__.py
maintain_PlatoUtils/v2/algorithms/GraphEmbeding.py
maintain_PlatoUtils/v2/algorithms/RelationRecognizer.py
maintain_PlatoUtils/v2/algorithms/__init__.py
maintain_PlatoUtils/v2/text_utils/__init__.py
maintain_PlatoUtils/v2/text_utils/afterprocessor.py
maintain_PlatoUtils/v2/text_utils/preprocessor.py
maintain_PlatoUtils/v2/text_utils/tryTfidfSearch.py
maintain_PlatoUtils/v2/text_utils/staticData/__init__.py
maintain_PlatoUtils/v2/text_utils/staticData/locImpDict.py
maintain_PlatoUtils/v2/text_utils/staticData/stopwords.py
maintain_PlatoUtils-0.1.3.100.dist-info/LICENSE
maintain_PlatoUtils-0.1.3.100.dist-info/METADATA
maintain_PlatoUtils-0.1.3.100.dist-info/WHEEL
maintain_PlatoUtils-0.1.3.100.dist-info/top_level.txt
maintain_PlatoUtils-0.1.3.100.dist-info/RECORD
